{
	"default_module": "powerline.segments.common",
	"segment_data": {
		"uptime": {
			"before": "⇑  "
		},
		"external_ip": {
			"before": "ⓦ  "
		},
		"email_imap_alert": {
			"before": "✉ ",
			"args": {
				"username": "",
				"password": ""
			}
		}
	},
	"segments": {
		"right": [
			{
				"name": "date",
				"args": {
					"format": "Week-%V"
				}
			},
			{
				"name": "date",
				"args": {
					"format": "%a"
				}
			},
			{
				"name": "date",
				"args": {
					"format": "%d-%b-%Y"
				}
			},
			{
				"name": "date",
				"args": {
					"format": "%I:%M%p %Z",
					"istime": true
				}
			}
		]
	}
}
